logicsdk_sage/__init__.py
logicsdk_sage/main.py
logicsdk_sage/summarizer.py
logicsdk_sage-0.0.2.dist-info/LICENSE
logicsdk_sage-0.0.2.dist-info/METADATA
logicsdk_sage-0.0.2.dist-info/WHEEL
logicsdk_sage-0.0.2.dist-info/top_level.txt
logicsdk_sage-0.0.2.dist-info/RECORD
